[
  {
    "order_id": "ORD001",
    "user_id": "USR001",
    "estimated_arrival": "2024-12-20",
    "transaction_date": "2024-12-15"
  },
  {
    "order_id": "ORD002",
    "user_id": "USR002",
    "estimated_arrival": "2024-12-21",
    "transaction_date": "2024-12-16"
  },
  {
    "order_id": "ORD003",
    "user_id": "USR003",
    "estimated_arrival": "2024-12-22",
    "transaction_date": "2024-12-17"
  },
  {
    "order_id": "ORD004",
    "user_id": "USR001",
    "estimated_arrival": "2024-12-23",
    "transaction_date": "2024-12-18"
  },
  {
    "order_id": "ORD005",
    "user_id": "USR004",
    "estimated_arrival": "2024-12-24",
    "transaction_date": "2024-12-19"
  },
  {
    "order_id": "ORD006",
    "user_id": "USR005",
    "estimated_arrival": "2024-12-25",
    "transaction_date": "2024-12-20"
  },
  {
    "order_id": "ORD007",
    "user_id": "USR002",
    "estimated_arrival": "2024-12-26",
    "transaction_date": "2024-12-21"
  },
  {
    "order_id": "ORD008",
    "user_id": "USR003",
    "estimated_arrival": "2024-12-27",
    "transaction_date": "2024-12-22"
  },
  {
    "order_id": "ORD009",
    "user_id": "USR004",
    "estimated_arrival": "2024-12-28",
    "transaction_date": "2024-12-23"
  },
  {
    "order_id": "ORD010",
    "user_id": "USR005",
    "estimated_arrival": "2024-12-29",
    "transaction_date": "2024-12-24"
  }
]
